odoo8_addon_web_last_viewed_records-8.0.1.0.0-py2.7-nspkg.pth
odoo_addons/web_last_viewed_records/views.xml
odoo_addons/web_last_viewed_records/__openerp__.py
odoo_addons/web_last_viewed_records/__init__.py
odoo_addons/web_last_viewed_records/README.rst
odoo_addons/web_last_viewed_records/static/description/icon.png
odoo_addons/web_last_viewed_records/static/src/js/main.js
odoo_addons/web_last_viewed_records/static/src/css/main.css
odoo_addons/web_last_viewed_records/static/src/xml/main.xml
odoo8_addon_web_last_viewed_records-8.0.1.0.0.dist-info/top_level.txt
odoo8_addon_web_last_viewed_records-8.0.1.0.0.dist-info/WHEEL
odoo8_addon_web_last_viewed_records-8.0.1.0.0.dist-info/RECORD
odoo8_addon_web_last_viewed_records-8.0.1.0.0.dist-info/metadata.json
odoo8_addon_web_last_viewed_records-8.0.1.0.0.dist-info/DESCRIPTION.rst
odoo8_addon_web_last_viewed_records-8.0.1.0.0.dist-info/METADATA
odoo8_addon_web_last_viewed_records-8.0.1.0.0.dist-info/namespace_packages.txt
