Metadata-Version: 2.0
Name: odoo8-addon-web-last-viewed-records
Version: 8.0.1.0.0
Summary: Last viewed records
Home-page: https://yelizariev.github.io
Author: UNKNOWN
Author-email: UNKNOWN
License: UNKNOWN
Platform: UNKNOWN
Requires-Dist: odoo (<9.0a,>=8.0a)
Classifier: Programming Language :: Python :: 2.7
Classifier: Framework :: Odoo
